propoptics-0.1.3.dist-info/METADATA
propoptics-0.1.3.dist-info/WHEEL
propoptics-0.1.3.dist-info/entry_points.txt
propoptics-0.1.3.dist-info/licenses/LICENSE
propoptics/_propoptics.py
propoptics/interface.py
propoptics/__init__.py
propoptics/math.py
propoptics/__main__.py
propoptics/_lib_propoptics.abi3.so
propoptics-0.1.3.dist-info/RECORD
