Metadata-Version: 2.4
Name: propoptics
Version: 0.1.3
Classifier: License :: OSI Approved :: MIT License
Classifier: Development Status :: 3 - Alpha
Classifier: Intended Audience :: Science/Research
Classifier: Topic :: Education
Classifier: Topic :: Scientific/Engineering :: Physics
Classifier: Programming Language :: Rust
Classifier: Programming Language :: Python
Classifier: Programming Language :: Python :: 3
Classifier: Programming Language :: Python :: 3 :: Only
Classifier: Programming Language :: Python :: 3.11
Classifier: Programming Language :: Python :: 3.12
Classifier: Programming Language :: Python :: 3.13
Classifier: Typing :: Typed
Classifier: Operating System :: OS Independent
Requires-Dist: matplotlib>=3.10.1
Requires-Dist: numpy>=1.26.0
Requires-Dist: scipy>=1.12.0
Requires-Dist: click<8.2.0
Requires-Dist: typer>=0.15.3
License-File: LICENSE
Summary: Generate noise signal based on PSD measurement and analyze the output
Keywords: noise,dsp,spectrum,optical,optics,nonlinear,laser,pulse
Author-email: Benoît Sierro <benoit.sierro@bluewin.ch>
Requires-Python: >=3.11
